{
  "timestamp": "2026-02-25T08:45:00+00:00",
  "indices": {
    "US30": [
      { "symbol": "AAPL", "change": 1.2, "status": "BUY" },
      { "symbol": "MSFT", "change": -0.5, "status": "SELL" },
      { "symbol": "JPM", "change": 0.8, "status": "BUY" },
      { "symbol": "V", "change": -1.1, "status": "SELL" }
    ],
    "HK50": [
      { "symbol": "0005.HK", "change": 0.6, "status": "BUY" },
      { "symbol": "0941.HK", "change": -0.3, "status": "SELL" },
      { "symbol": "1299.HK", "change": 1.0, "status": "BUY" },
      { "symbol": "3988.HK", "change": -0.7, "status": "SELL" }
    ]
  }
}
